octopod/__init__.py
octopod/_version.py
octopod/dataloader.py
octopod/exc.py
octopod/learner.py
octopod/ensemble/__init__.py
octopod/ensemble/dataset.py
octopod/ensemble/models/__init__.py
octopod/ensemble/models/multi_task_ensemble.py
octopod/learner_utils/__init__.py
octopod/learner_utils/loss_metrics_utils_config.py
octopod/learner_utils/metrics_utils.py
octopod/text/__init__.py
octopod/text/dataset.py
octopod/text/models/__init__.py
octopod/text/models/multi_task_bert.py
octopod/vision/__init__.py
octopod/vision/config.py
octopod/vision/dataset.py
octopod/vision/helpers.py
octopod/vision/models/__init__.py
octopod/vision/models/multi_task_resnet.py
octopod-3.2.0.data/data/LICENSE
tests/fixtures/__init__.py
tests/fixtures/learner_fixtures.py
tests/fixtures/model_preds_fixtures.py
octopod-3.2.0.dist-info/LICENSE
octopod-3.2.0.dist-info/METADATA
octopod-3.2.0.dist-info/WHEEL
octopod-3.2.0.dist-info/top_level.txt
octopod-3.2.0.dist-info/RECORD
