Metadata-Version: 2.1
Name: octopod
Version: 3.2.0
Summary: General purpose multi-task classification library
Home-page: https://github.com/shoprunner/octopod
Author: Nicole Carlson, Michael Sugimura
License: BSD-3-Clause
Platform: UNKNOWN
License-File: LICENSE
Requires-Dist: fastprogress
Requires-Dist: ipywidgets
Requires-Dist: joblib
Requires-Dist: markupsafe (<2.1)
Requires-Dist: matplotlib
Requires-Dist: numpy
Requires-Dist: Pillow (<7.0.0)
Requires-Dist: sentencepiece (!=0.1.92)
Requires-Dist: scikit-learn
Requires-Dist: torch
Requires-Dist: torchvision (==0.2.1)
Requires-Dist: transformers (<3.0.0,>=2.3.0)
Requires-Dist: wildebeest
